datastorage/__init__.py
datastorage/datastorage.py
datastorage/datastorage_int.py
datastorage/examples.py
datastorage/prolem.py
datastorage/test.py
datastorage-0.4.9.dist-info/LICENSE
datastorage-0.4.9.dist-info/METADATA
datastorage-0.4.9.dist-info/WHEEL
datastorage-0.4.9.dist-info/top_level.txt
datastorage-0.4.9.dist-info/RECORD
