Metadata-Version: 2.1
Name: datastorage
Version: 0.4.9
Summary: Dict-like object that can be saved in hdf5 or numpy format
Home-page: https://github.com/marcocamma/datastorage
Author: marco cammarata
Author-email: marcocammarata@gmail.com
License: MIT
Platform: UNKNOWN
Requires-Dist: h5py
Requires-Dist: numpy
